__init__.py
harreveltools/__init__.py
harreveltools/analytics.py
harreveltools/data_transform.py
harreveltools/display.py
harreveltools/file_handling.py
harreveltools/metric.py
harreveltools/plot.py
harreveltools-0.0.5.dist-info/LICENSE
harreveltools-0.0.5.dist-info/METADATA
harreveltools-0.0.5.dist-info/WHEEL
harreveltools-0.0.5.dist-info/top_level.txt
harreveltools-0.0.5.dist-info/RECORD
