Metadata-Version: 2.1
Name: harreveltools
Version: 0.0.5
Summary: This package is the result of sweat and tears
Author-email: S Harrevelt <author@example.com>
Project-URL: Homepage, https://github.com/zwep
Project-URL: Bug Tracker, https://github.com/zwep
Classifier: Programming Language :: Python :: 3
Classifier: License :: OSI Approved :: MIT License
Classifier: Operating System :: OS Independent
Requires-Python: >=3.8
License-File: LICENSE
